LICENSE
README.rst
setup.py
quantverse/__init__.py
quantverse/scratch.py
quantverse/version.py
quantverse.egg-info/PKG-INFO
quantverse.egg-info/SOURCES.txt
quantverse.egg-info/dependency_links.txt
quantverse.egg-info/requires.txt
quantverse.egg-info/top_level.txt
quantverse/core/__init__.py
quantverse/core/model.py
quantverse/models/__init__.py
quantverse/models/brownian.py
quantverse/models/bsm.py
quantverse/models/mc.py
quantverse/util/__init__.py
quantverse/util/builder.py