Metadata-Version: 2.1
Name: quantverse
Version: 0.0.1
Summary: quantverse: Quantitative Finance in Python
Home-page: https://anyoptimization.com/projects/quantverse/
Author: Julian Blank
Author-email: blankjul@outlook.com
License: GNU AFFERO GENERAL PUBLIC LICENSE (AGPL)
Keywords: quantitative,finance,stocks,options,
Platform: any
Classifier: Intended Audience :: Developers
Classifier: Intended Audience :: Science/Research
Classifier: Intended Audience :: Financial and Insurance Industry
Classifier: Intended Audience :: Science/Research
Classifier: Operating System :: OS Independent
Classifier: License :: OSI Approved :: Apache Software License
Classifier: Programming Language :: Python
Classifier: Programming Language :: Python :: 3
Classifier: Topic :: Scientific/Engineering
Classifier: Topic :: Scientific/Engineering :: Artificial Intelligence
Classifier: Topic :: Scientific/Engineering :: Mathematics
Requires-Python: >=3.7
License-File: LICENSE
Requires-Dist: pandas>=2.2
